SciAnalysis/Base.py
SciAnalysis/Data.py
SciAnalysis/Fit.py
SciAnalysis/IO_HDF.py
SciAnalysis/Result.py
SciAnalysis/__init__.py
SciAnalysis/_version.py
SciAnalysis/colormaps.py
SciAnalysis/settings.py
SciAnalysis/tools.py
SciAnalysis/XSAnalysis/Data.py
SciAnalysis/XSAnalysis/DataGonio.py
SciAnalysis/XSAnalysis/DataQ.py
SciAnalysis/XSAnalysis/DataRQconv.py
SciAnalysis/XSAnalysis/Eiger-alternate.py
SciAnalysis/XSAnalysis/Eiger.py
SciAnalysis/XSAnalysis/Multiple.py
SciAnalysis/XSAnalysis/Protocols.py
SciAnalysis/XSAnalysis/__init__.py
SciToolsSciAnalysis-2.6.6.dist-info/LICENSE
SciToolsSciAnalysis-2.6.6.dist-info/METADATA
SciToolsSciAnalysis-2.6.6.dist-info/WHEEL
SciToolsSciAnalysis-2.6.6.dist-info/entry_points.txt
SciToolsSciAnalysis-2.6.6.dist-info/top_level.txt
SciToolsSciAnalysis-2.6.6.dist-info/RECORD
