Metadata-Version: 2.1
Name: SciToolsSciAnalysis
Version: 2.6.6
Summary: SciAnalysis scripts for processing image files.
Home-page: https://github.com/CFN-softbio/SciAnalysis
Author: Kevin Yager
Author-email: kyager@bnl.gov
License: BSD (3-clause)
Keywords: Analysis
Platform: UNKNOWN
Classifier: Development Status :: 5 - Production/Stable
Classifier: Natural Language :: English
Classifier: Programming Language :: Python :: 3
Requires-Python: >=3.7
Requires-Dist: matplotlib
Requires-Dist: numpy
Requires-Dist: scipy
